tests/__init__.py
tests/test_data_flow.py
tests/test_mitigations.py
tests/test_project.py
tests/test_serialization.py
tests/test_threats.py
tests/enumeration/__init__.py
tests/enumeration/test_stride.py
threat_modeling/__init__.py
threat_modeling/data_flow.py
threat_modeling/exceptions.py
threat_modeling/mitigations.py
threat_modeling/project.py
threat_modeling/serialization.py
threat_modeling/threats.py
threat_modeling/enumeration/base.py
threat_modeling/enumeration/stride.py
threat_modeling-0.0.1.data/scripts/threatmodel
threat_modeling-0.0.1.dist-info/LICENSE
threat_modeling-0.0.1.dist-info/METADATA
threat_modeling-0.0.1.dist-info/WHEEL
threat_modeling-0.0.1.dist-info/top_level.txt
threat_modeling-0.0.1.dist-info/RECORD
