Metadata-Version: 2.1
Name: threat-modeling
Version: 0.0.1
Summary: Threat modeling tools
Home-page: https://github.com/redshiftzero/threat-modeling
Author: redshiftzero
Author-email: jen@redshiftzero.com
License: UNKNOWN
Platform: UNKNOWN
Classifier: Programming Language :: Python :: 3
Classifier: Development Status :: 3 - Alpha
Classifier: Topic :: Security
Classifier: Topic :: Scientific/Engineering :: Visualization
Classifier: License :: OSI Approved :: GNU General Public License v3 (GPLv3)
Classifier: Operating System :: OS Independent
Requires-Python: >=3.7
Requires-Dist: pygraphviz (>=1.5)
Requires-Dist: PyYAML (>=5.3)
